{"61118": ["Bad Vilbel", "Bad Vilbel (Hessen)", "Dortelweil", "Gronau", "Heilsberg", "Massenheim"], 
"61130": ["Erbstadt", "Heldenbergen", "Hessen-Nidderau", "Nidderau", "Ostheim", "Windecken", "Winnerh\u00f6fe"], 
"61137": ["B\u00fcdesheim", "Hessen-Sch\u00f6neck", "Kilianst\u00e4dten", "Oberdorfelden", "Sch\u00f6neck"], 
"61138": ["Hessen-Niederdorfelden", "Niederdorfelden"], 
"61169": ["Bauernheim", "Bruchenbr\u00fccken", "Dorheim (Friedberg)", "Friedberg", "Friedberg (Hessen)", "Hessen-Friedberg", "Ockstadt", "Ossenheim"], 
"61184": ["Burg-Gr\u00e4fenrode", "Gro\u00df-Karben", "Hessen-Karben", "Karben", "Klein-Karben", "Kloppenheim", "Okarben", "Petterweil", "Rendel"], 
"61191": ["Hessen-Rosbach", "Nieder-Rosbach", "Ober-Rosbach", "Rodheim vor der H\u00f6he", "Rosbach", "Rosbach vor der H\u00f6he"], 
"61194": ["Assenheim", "B\u00f6nstadt", "Hessen-Niddatal", "Ilbenstadt", "Kaichen", "Niddatal"], 
"61197": ["Florstadt", "Hessen-Florstadt", "Leidhecken", "Nieder-Florstadt", "Nieder-Mockstadt", "Ober-Florstadt", "Staden (Florstadt)", "Stammheim"], 
"61200": ["Am R\u00f6merhof", "Am R\u00f6merschacht", "Berstadt", "Echzell", "Hessen-Echzell", "Hessen-W\u00f6lfersheim", "Melbach", "S\u00f6del", "Wohnbach", "W\u00f6lfersheim"], 
"61203": ["Beienheim", "Bingenheimer M\u00fchle", "Blofeld", "Dorn-Assenheim", "Eiserhof", "Hessen-Reichelsheim", "Heuchelheim (Reichelsheim)", "Reichelsheim", "Reichelsheim (Wetterau)", "Weckesheim", "Winterhof"], 
"61206": ["Hessen-W\u00f6llstadt", "Nieder-W\u00f6llstadt", "Ober-W\u00f6llstadt", "W\u00f6llstadt"], 
"61209": ["Bingenheim", "Bisses", "Echzell", "Gettenau", "Grund-Schwalheim", "Kreuzquelle"], 
"61231": ["Bad Nauheim", "Bad Nauheim (Hessen)", "Nieder-M\u00f6rlen", "R\u00f6dgen", "Schwalheim", "Steinfurth", "Wisselsheim"], 
"61239": ["Langenhain-Ziegenberg", "Ober-M\u00f6rlen", "Ober-M\u00f6rlen (Hessen)"], 
"61250": ["Erdfunkstelle Usingen", "Hessen-Usingen", "Usingen"], 
"61267": ["Neu-Anspach", "Neu-Anspach (Hessen)"], 
"61273": ["Friedrichsdorf", "Hessen-Friedrichsdorf", "Hessen-Wehrheim", "Saalburg", "Wehrheim"], 
"61276": ["Hessen-Weilrod", "Weilrod"], 
"61279": ["Gr\u00e4venwiesbach", "Hessen-Gr\u00e4venwiesbach"], 
"61348": ["Bad Homburg", "Bad Homburg (Hochtaunuskreis)", "Berliner Siedlung/Gartenfeld"], 
"61350": ["Bad Homburg"], 
"61352": ["Bad Homburg"], 
"61381": ["Dillingen", "Friedrichsdorf", "Hochtaunuskreis-Friedrichsdorf"], 
"61389": ["Hochtaunuskreis-Schmitten", "Schmitten", "Schmitten im Taunus"], 
"61440": ["Hochtaunuskreis-Oberursel", "Oberursel", "Oberursel (Taunus)"], 
"61449": ["Hochtaunuskreis-Steinbach", "Steinbach", "Steinbach (Taunus)"], 
"61462": ["Hochtaunuskreis-K\u00f6nigstein", "K\u00f6nigstein", "K\u00f6nigstein im Taunus"], 
"61476": ["Hochtaunuskreis-Kronberg", "Kronberg", "Kronberg im Taunus"], 
"61479": ["Glash\u00fctten", "Hochtaunuskreis-Glash\u00fctten"]}