[{"ags": "03355049", "area": 237.96, "email": null, "gemeinde": "Amt Neuhaus", "name": null, "ort": "Neuhaus/Elbe", "phone": null, "plz": "19273", "population": 5074, "sitz": "Gemeinde Amt Neuhaus", "str": "Am Markt 4"}, 
{"ags": "12070173", "area": 253.55, "email": null, "gemeinde": "Karstädt", "name": null, "ort": "Karstädt", "phone": null, "plz": "19357", "population": 5898, "sitz": "Gemeinde Karstädt", "str": "Mühlenstraße 1"}, 
{"ags": "12070296", "area": 138.69, "email": null, "gemeinde": "Perleberg, Stadt", "name": null, "ort": "Perleberg", "phone": null, "plz": "19348", "population": 12007, "sitz": "Stadtverwaltung Perleberg", "str": "Großer Markt"}, 
{"ags": "12070302", "area": 202, "email": null, "gemeinde": "Plattenburg", "name": null, "ort": "Plattenburg OT Kletzke", "phone": null, "plz": "19339", "population": 3290, "sitz": "Gemeinde Plattenburg", "str": "Dorfstraße 52a"}, 
{"ags": "12070424", "area": 50.63, "email": null, "gemeinde": "Wittenberge, Stadt", "name": null, "ort": "Wittenberge", "phone": null, "plz": "19322", "population": 16682, "sitz": "Stadtverwaltung Wittenberge", "str": "August-Bebel-Straße 10"}, 
{"ags": "12070008", "area": 79.62, "email": null, "gemeinde": "Bad Wilsnack, Stadt", "name": null, "ort": "Bad Wilsnack", "phone": null, "plz": "19336", "population": 2536, "sitz": "Amt Bad Wilsnack/Weisen", "str": "Am Markt 1"}, 
{"ags": "12070052", "area": 23.76, "email": null, "gemeinde": "Breese", "name": null, "ort": "Bad Wilsnack", "phone": null, "plz": "19336", "population": 1487, "sitz": "Amt Bad Wilsnack/Weisen", "str": "Am Markt 1"}, 
{"ags": "12070241", "area": 41.74, "email": null, "gemeinde": "Legde/Quitzöbel", "name": null, "ort": "Bad Wilsnack", "phone": null, "plz": "19336", "population": 600, "sitz": "Amt Bad Wilsnack/Weisen", "str": "Am Markt 1"}, 
{"ags": "12070348", "area": 28.99, "email": null, "gemeinde": "Rühstädt", "name": null, "ort": "Bad Wilsnack", "phone": null, "plz": "19336", "population": 463, "sitz": "Amt Bad Wilsnack/Weisen", "str": "Am Markt 1"}, 
{"ags": "12070416", "area": 15.63, "email": null, "gemeinde": "Weisen", "name": null, "ort": "Bad Wilsnack", "phone": null, "plz": "19336", "population": 976, "sitz": "Amt Bad Wilsnack/Weisen", "str": "Am Markt 1"}, 
{"ags": "12070060", "area": 22.18, "email": null, "gemeinde": "Cumlosen", "name": null, "ort": "Lenzen", "phone": null, "plz": "19309", "population": 717, "sitz": "Amt Lenzen-Elbtalaue", "str": "Kellerstraße 4"}, 
{"ags": "12070236", "area": 60.35, "email": null, "gemeinde": "Lanz", "name": null, "ort": "Lenzen", "phone": null, "plz": "19309", "population": 696, "sitz": "Amt Lenzen-Elbtalaue", "str": "Kellerstraße 4"}, 
{"ags": "12070244", "area": 96.19, "email": null, "gemeinde": "Lenzen (Elbe), Stadt", "name": null, "ort": "Lenzen", "phone": null, "plz": "19309", "population": 2058, "sitz": "Amt Lenzen-Elbtalaue", "str": "Kellerstraße 4"}, 
{"ags": "12070246", "area": 42.07, "email": null, "gemeinde": "Lenzerwische", "name": null, "ort": "Lenzen", "phone": null, "plz": "19309", "population": 460, "sitz": "Amt Lenzen-Elbtalaue", "str": "Kellerstraße 4"}, 
{"ags": "13004000", "area": 130.52, "email": null, "gemeinde": "Schwerin, Landeshauptstadt", "name": null, "ort": "Schwerin", "phone": null, "plz": "19053", "population": 95740, "sitz": "Landeshauptstadt Schwerin", "str": "Am Packhof 2-6"}, 
{"email": "buergerbuero@schwerin.de", "name": "Schwerin", "ort": "Schwerin", "phone": "0385-545-1111", "plz": "19053", "prefix": "Bürgeramt", "str": "Am Packhof 2-6"}, 
{"ags": "13074020", "area": 20.62, "email": null, "gemeinde": "Dragun", "name": null, "ort": "Gadebusch", "phone": null, "plz": "19205", "population": 759, "sitz": "Amt Gadebusch", "str": "Am Markt 1"}, 
{"ags": "13074021", "area": 47.76, "email": null, "gemeinde": "Gadebusch, Stadt", "name": null, "ort": "Gadebusch", "phone": null, "plz": "19205", "population": 5417, "sitz": "Amt Gadebusch", "str": "Am Markt 1"}, 
{"ags": "13074040", "area": 15.87, "email": null, "gemeinde": "Kneese", "name": null, "ort": "Gadebusch", "phone": null, "plz": "19205", "population": 357, "sitz": "Amt Gadebusch", "str": "Am Markt 1"}, 
{"ags": "13074043", "area": 39.16, "email": null, "gemeinde": "Krembz", "name": null, "ort": "Gadebusch", "phone": null, "plz": "19205", "population": 881, "sitz": "Amt Gadebusch", "str": "Am Markt 1"}, 
{"ags": "13074054", "area": 23.71, "email": null, "gemeinde": "Mühlen Eichsen", "name": null, "ort": "Gadebusch", "phone": null, "plz": "19205", "population": 978, "sitz": "Amt Gadebusch", "str": "Am Markt 1"}, 
{"ags": "13074068", "area": 31.26, "email": null, "gemeinde": "Roggendorf", "name": null, "ort": "Gadebusch", "phone": null, "plz": "19205", "population": 1049, "sitz": "Amt Gadebusch", "str": "Am Markt 1"}, 
{"ags": "13074070", "area": 11.43, "email": null, "gemeinde": "Rögnitz", "name": null, "ort": "Gadebusch", "phone": null, "plz": "19205", "population": 189, "sitz": "Amt Gadebusch", "str": "Am Markt 1"}, 
{"ags": "13074081", "area": 32.62, "email": null, "gemeinde": "Veelböken", "name": null, "ort": "Gadebusch", "phone": null, "plz": "19205", "population": 641, "sitz": "Amt Gadebusch", "str": "Am Markt 1"}, 
{"ags": "13074001", "area": 23.22, "email": null, "gemeinde": "Alt Meteln", "name": null, "ort": "Lützow", "phone": null, "plz": "19209", "population": 1172, "sitz": "Amt Lützow-Lübstorf", "str": "Dorfmitte 24"}, 
{"ags": "13074012", "area": 29.94, "email": null, "gemeinde": "Brüsewitz", "name": null, "ort": "Lützow", "phone": null, "plz": "19209", "population": 1967, "sitz": "Amt Lützow-Lübstorf", "str": "Dorfmitte 24"}, 
{"ags": "13074014", "area": 10.2, "email": null, "gemeinde": "Cramonshagen", "name": null, "ort": "Lützow", "phone": null, "plz": "19209", "population": 520, "sitz": "Amt Lützow-Lübstorf", "str": "Dorfmitte 24"}, 
{"ags": "13074015", "area": 9.59, "email": null, "gemeinde": "Dalberg-Wendelstorf", "name": null, "ort": "Lützow", "phone": null, "plz": "19209", "population": 543, "sitz": "Amt Lützow-Lübstorf", "str": "Dorfmitte 24"}, 
{"ags": "13074024", "area": 22.21, "email": null, "gemeinde": "Gottesgabe", "name": null, "ort": "Lützow", "phone": null, "plz": "19209", "population": 749, "sitz": "Amt Lützow-Lübstorf", "str": "Dorfmitte 24"}, 
{"ags": "13074025", "area": 19.82, "email": null, "gemeinde": "Grambow", "name": null, "ort": "Lützow", "phone": null, "plz": "19209", "population": 654, "sitz": "Amt Lützow-Lübstorf", "str": "Dorfmitte 24"}, 
{"ags": "13074038", "area": 25.38, "email": null, "gemeinde": "Klein Trebbow", "name": null, "ort": "Lützow", "phone": null, "plz": "19209", "population": 1123, "sitz": "Amt Lützow-Lübstorf", "str": "Dorfmitte 24"}, 
{"ags": "13074048", "area": 43.88, "email": null, "gemeinde": "Lübstorf", "name": null, "ort": "Lützow", "phone": null, "plz": "19209", "population": 1463, "sitz": "Amt Lützow-Lübstorf", "str": "Dorfmitte 24"}, 
{"ags": "13074050", "area": 24.89, "email": null, "gemeinde": "Lützow", "name": null, "ort": "Lützow", "phone": null, "plz": "19209", "population": 1560, "sitz": "Amt Lützow-Lübstorf", "str": "Dorfmitte 24"}, 
{"ags": "13074061", "area": 13.46, "email": null, "gemeinde": "Perlin", "name": null, "ort": "Lützow", "phone": null, "plz": "19209", "population": 379, "sitz": "Amt Lützow-Lübstorf", "str": "Dorfmitte 24"}, 
{"ags": "13074062", "area": 2.08, "email": null, "gemeinde": "Pingelshagen", "name": null, "ort": "Lützow", "phone": null, "plz": "19209", "population": 531, "sitz": "Amt Lützow-Lübstorf", "str": "Dorfmitte 24"}, 
{"ags": "13074064", "area": 15.65, "email": null, "gemeinde": "Pokrent", "name": null, "ort": "Lützow", "phone": null, "plz": "19209", "population": 685, "sitz": "Amt Lützow-Lübstorf", "str": "Dorfmitte 24"}, 
{"ags": "13074072", "area": 19.38, "email": null, "gemeinde": "Schildetal", "name": null, "ort": "Lützow", "phone": null, "plz": "19209", "population": 764, "sitz": "Amt Lützow-Lübstorf", "str": "Dorfmitte 24"}, 
{"ags": "13074075", "area": 4.35, "email": null, "gemeinde": "Seehof", "name": null, "ort": "Lützow", "phone": null, "plz": "19209", "population": 939, "sitz": "Amt Lützow-Lübstorf", "str": "Dorfmitte 24"}, 
{"ags": "13074088", "area": 12.49, "email": null, "gemeinde": "Zickhusen", "name": null, "ort": "Lützow", "phone": null, "plz": "19209", "population": 520, "sitz": "Amt Lützow-Lübstorf", "str": "Dorfmitte 24"}, 
{"ags": "13074013", "area": 31.81, "email": null, "gemeinde": "Carlow", "name": null, "ort": "Rehna", "phone": null, "plz": "19217", "population": 1223, "sitz": "Amt Rehna", "str": "Freiheitsplatz 1"}, 
{"ags": "13074018", "area": 15.15, "email": null, "gemeinde": "Dechow", "name": null, "ort": "Rehna", "phone": null, "plz": "19217", "population": 191, "sitz": "Amt Rehna", "str": "Freiheitsplatz 1"}, 
{"ags": "13074028", "area": 6.31, "email": null, "gemeinde": "Groß Molzahn", "name": null, "ort": "Rehna", "phone": null, "plz": "19217", "population": 394, "sitz": "Amt Rehna", "str": "Freiheitsplatz 1"}, 
{"ags": "13074033", "area": 13.57, "email": null, "gemeinde": "Holdorf", "name": null, "ort": "Rehna", "phone": null, "plz": "19217", "population": 399, "sitz": "Amt Rehna", "str": "Freiheitsplatz 1"}, 
{"ags": "13074042", "area": 32.75, "email": null, "gemeinde": "Königsfeld", "name": null, "ort": "Rehna", "phone": null, "plz": "19217", "population": 974, "sitz": "Amt Rehna", "str": "Freiheitsplatz 1"}, 
{"ags": "13074065", "area": 44.59, "email": null, "gemeinde": "Rehna, Stadt", "name": null, "ort": "Rehna", "phone": null, "plz": "19217", "population": 3598, "sitz": "Amt Rehna", "str": "Freiheitsplatz 1"}, 
{"ags": "13074066", "area": 12.32, "email": null, "gemeinde": "Rieps", "name": null, "ort": "Rehna", "phone": null, "plz": "19217", "population": 357, "sitz": "Amt Rehna", "str": "Freiheitsplatz 1"}, 
{"ags": "13074073", "area": 20.44, "email": null, "gemeinde": "Schlagsdorf", "name": null, "ort": "Rehna", "phone": null, "plz": "19217", "population": 1203, "sitz": "Amt Rehna", "str": "Freiheitsplatz 1"}, 
{"ags": "13074078", "area": 9.09, "email": null, "gemeinde": "Thandorf", "name": null, "ort": "Rehna", "phone": null, "plz": "19217", "population": 185, "sitz": "Amt Rehna", "str": "Freiheitsplatz 1"}, 
{"ags": "13074080", "area": 11.09, "email": null, "gemeinde": "Utecht", "name": null, "ort": "Rehna", "phone": null, "plz": "19217", "population": 429, "sitz": "Amt Rehna", "str": "Freiheitsplatz 1"}, 
{"ags": "13074092", "area": 24.92, "email": null, "gemeinde": "Wedendorfersee", "name": null, "ort": "Rehna", "phone": null, "plz": "19217", "population": 678, "sitz": "Amt Rehna", "str": "Freiheitsplatz 1"}, 
{"ags": "13076014", "area": 47.42, "email": null, "gemeinde": "Boizenburg/ Elbe, Stadt", "name": null, "ort": "Boizenburg/Elbe", "phone": null, "plz": "19258", "population": 10689, "sitz": "Stadt Boizenburg/Elbe", "str": "Kirchplatz 1"}, 
{"ags": "13076009", "area": 32.95, "email": null, "gemeinde": "Bengerstorf", "name": null, "ort": "Boizenburg/Elbe", "phone": null, "plz": "19258", "population": 537, "sitz": "Amt Boizenburg-Land", "str": "Fritz-Reuter-Straße 3"}, 
{"ags": "13076010", "area": 22.26, "email": null, "gemeinde": "Besitz", "name": null, "ort": "Boizenburg/Elbe", "phone": null, "plz": "19258", "population": 452, "sitz": "Amt Boizenburg-Land", "str": "Fritz-Reuter-Straße 3"}, 
{"ags": "13076016", "area": 21.96, "email": null, "gemeinde": "Brahlstorf", "name": null, "ort": "Boizenburg/Elbe", "phone": null, "plz": "19258", "population": 720, "sitz": "Amt Boizenburg-Land", "str": "Fritz-Reuter-Straße 3"}, 
{"ags": "13076030", "area": 22.51, "email": null, "gemeinde": "Dersenow", "name": null, "ort": "Boizenburg/Elbe", "phone": null, "plz": "19258", "population": 470, "sitz": "Amt Boizenburg-Land", "str": "Fritz-Reuter-Straße 3"}, 
{"ags": "13076054", "area": 21.08, "email": null, "gemeinde": "Gresse", "name": null, "ort": "Boizenburg/Elbe", "phone": null, "plz": "19258", "population": 722, "sitz": "Amt Boizenburg-Land", "str": "Fritz-Reuter-Straße 3"}, 
{"ags": "13076055", "area": 40.09, "email": null, "gemeinde": "Greven", "name": null, "ort": "Boizenburg/Elbe", "phone": null, "plz": "19258", "population": 737, "sitz": "Amt Boizenburg-Land", "str": "Fritz-Reuter-Straße 3"}, 
{"ags": "13076102", "area": 13.07, "email": null, "gemeinde": "Neu Gülze", "name": null, "ort": "Boizenburg/Elbe", "phone": null, "plz": "19258", "population": 764, "sitz": "Amt Boizenburg-Land", "str": "Fritz-Reuter-Straße 3"}, 
{"ags": "13076106", "area": 20.1, "email": null, "gemeinde": "Nostorf", "name": null, "ort": "Boizenburg/Elbe", "phone": null, "plz": "19258", "population": 714, "sitz": "Amt Boizenburg-Land", "str": "Fritz-Reuter-Straße 3"}, 
{"ags": "13076122", "area": 26.63, "email": null, "gemeinde": "Schwanheide", "name": null, "ort": "Boizenburg/Elbe", "phone": null, "plz": "19258", "population": 741, "sitz": "Amt Boizenburg-Land", "str": "Fritz-Reuter-Straße 3"}, 
{"ags": "13076136", "area": 27.55, "email": null, "gemeinde": "Teldau", "name": null, "ort": "Boizenburg/Elbe", "phone": null, "plz": "19258", "population": 981, "sitz": "Amt Boizenburg-Land", "str": "Fritz-Reuter-Straße 3"}, 
{"ags": "13076138", "area": 10.25, "email": null, "gemeinde": "Tessin b. Boizenburg", "name": null, "ort": "Boizenburg/Elbe", "phone": null, "plz": "19258", "population": 404, "sitz": "Amt Boizenburg-Land", "str": "Fritz-Reuter-Straße 3"}, 
{"ags": "13076060", "area": 67.54, "email": null, "gemeinde": "Hagenow, Stadt", "name": null, "ort": "Hagenow", "phone": null, "plz": "19230", "population": 12146, "sitz": "Stadt Hagenow", "str": "Lange Straße 28-32"}, 
{"ags": "13076002", "area": 8.43, "email": null, "gemeinde": "Alt Zachun", "name": null, "ort": "Hagenow", "phone": null, "plz": "19230", "population": 363, "sitz": "Amt Hagenow-Land", "str": "Bahnhofstraße 25"}, 
{"ags": "13076004", "area": 17.43, "email": null, "gemeinde": "Bandenitz", "name": null, "ort": "Hagenow", "phone": null, "plz": "19230", "population": 492, "sitz": "Amt Hagenow-Land", "str": "Bahnhofstraße 25"}, 
{"ags": "13076008", "area": 22.59, "email": null, "gemeinde": "Belsch", "name": null, "ort": "Hagenow", "phone": null, "plz": "19230", "population": 221, "sitz": "Amt Hagenow-Land", "str": "Bahnhofstraße 25"}, 
{"ags": "13076013", "area": 6.09, "email": null, "gemeinde": "Bobzin", "name": null, "ort": "Hagenow", "phone": null, "plz": "19230", "population": 256, "sitz": "Amt Hagenow-Land", "str": "Bahnhofstraße 25"}, 
{"ags": "13076019", "area": 16.58, "email": null, "gemeinde": "Bresegard bei Picher", "name": null, "ort": "Hagenow", "phone": null, "plz": "19230", "population": 291, "sitz": "Amt Hagenow-Land", "str": "Bahnhofstraße 25"}, 
{"ags": "13076041", "area": 15.64, "email": null, "gemeinde": "Gammelin", "name": null, "ort": "Hagenow", "phone": null, "plz": "19230", "population": 477, "sitz": "Amt Hagenow-Land", "str": "Bahnhofstraße 25"}, 
{"ags": "13076057", "area": 10.4, "email": null, "gemeinde": "Groß Krams", "name": null, "ort": "Hagenow", "phone": null, "plz": "19230", "population": 167, "sitz": "Amt Hagenow-Land", "str": "Bahnhofstraße 25"}, 
{"ags": "13076064", "area": 22.25, "email": null, "gemeinde": "Hoort", "name": null, "ort": "Hagenow", "phone": null, "plz": "19230", "population": 600, "sitz": "Amt Hagenow-Land", "str": "Bahnhofstraße 25"}, 
{"ags": "13076065", "area": 9.09, "email": null, "gemeinde": "Hülseburg", "name": null, "ort": "Hagenow", "phone": null, "plz": "19230", "population": 160, "sitz": "Amt Hagenow-Land", "str": "Bahnhofstraße 25"}, 
{"ags": "13076070", "area": 18.95, "email": null, "gemeinde": "Kirch Jesar", "name": null, "ort": "Hagenow", "phone": null, "plz": "19230", "population": 639, "sitz": "Amt Hagenow-Land", "str": "Bahnhofstraße 25"}, 
{"ags": "13076079", "area": 15.09, "email": null, "gemeinde": "Kuhstorf", "name": null, "ort": "Hagenow", "phone": null, "plz": "19230", "population": 730, "sitz": "Amt Hagenow-Land", "str": "Bahnhofstraße 25"}, 
{"ags": "13076099", "area": 16.78, "email": null, "gemeinde": "Moraas", "name": null, "ort": "Hagenow", "phone": null, "plz": "19230", "population": 490, "sitz": "Amt Hagenow-Land", "str": "Bahnhofstraße 25"}, 
{"ags": "13076110", "area": 10.65, "email": null, "gemeinde": "Pätow-Steegen", "name": null, "ort": "Hagenow", "phone": null, "plz": "19230", "population": 411, "sitz": "Amt Hagenow-Land", "str": "Bahnhofstraße 25"}, 
{"ags": "13076111", "area": 39.09, "email": null, "gemeinde": "Picher", "name": null, "ort": "Hagenow", "phone": null, "plz": "19230", "population": 625, "sitz": "Amt Hagenow-Land", "str": "Bahnhofstraße 25"}, 
{"ags": "13076116", "area": 19.55, "email": null, "gemeinde": "Pritzier", "name": null, "ort": "Hagenow", "phone": null, "plz": "19230", "population": 459, "sitz": "Amt Hagenow-Land", "str": "Bahnhofstraße 25"}, 
{"ags": "13076119", "area": 17.71, "email": null, "gemeinde": "Redefin", "name": null, "ort": "Hagenow", "phone": null, "plz": "19230", "population": 540, "sitz": "Amt Hagenow-Land", "str": "Bahnhofstraße 25"}, 
{"ags": "13076131", "area": 14.76, "email": null, "gemeinde": "Strohkirchen", "name": null, "ort": "Hagenow", "phone": null, "plz": "19230", "population": 310, "sitz": "Amt Hagenow-Land", "str": "Bahnhofstraße 25"}, 
{"ags": "13076145", "area": 23.91, "email": null, "gemeinde": "Warlitz", "name": null, "ort": "Hagenow", "phone": null, "plz": "19230", "population": 452, "sitz": "Amt Hagenow-Land", "str": "Bahnhofstraße 25"}, 
{"ags": "13076169", "area": 31.66, "email": null, "gemeinde": "Toddin", "name": null, "ort": "Hagenow", "phone": null, "plz": "19230", "population": 917, "sitz": "Amt Hagenow-Land", "str": "Bahnhofstraße 25"}, 
{"ags": "13076088", "area": 120.16, "email": null, "gemeinde": "Lübtheen, Stadt", "name": null, "ort": "Lübtheen", "phone": null, "plz": "19249", "population": 4686, "sitz": "Stadt Lübtheen", "str": "Salzstraße 17"}, 
{"ags": "13076090", "area": 78.64, "email": null, "gemeinde": "Ludwigslust, Stadt", "name": null, "ort": "Ludwigslust", "phone": null, "plz": "19288", "population": 12070, "sitz": "Stadt Ludwigslust", "str": "Schloßstraße 38"}, 
{"ags": "13076001", "area": 37.9, "email": null, "gemeinde": "Alt Krenzlin", "name": null, "ort": "Ludwigslust", "phone": null, "plz": "19288", "population": 746, "sitz": "Amt Ludwigslust-Land", "str": "Wöbbeliner Straße 5"}, 
{"ags": "13076018", "area": 11.1, "email": null, "gemeinde": "Bresegard bei Eldena", "name": null, "ort": "Ludwigslust", "phone": null, "plz": "19288", "population": 199, "sitz": "Amt Ludwigslust-Land", "str": "Wöbbeliner Straße 5"}, 
{"ags": "13076046", "area": 34.02, "email": null, "gemeinde": "Göhlen", "name": null, "ort": "Ludwigslust", "phone": null, "plz": "19288", "population": 559, "sitz": "Amt Ludwigslust-Land", "str": "Wöbbeliner Straße 5"}, 
{"ags": "13076058", "area": 27.42, "email": null, "gemeinde": "Groß Laasch", "name": null, "ort": "Ludwigslust", "phone": null, "plz": "19288", "population": 972, "sitz": "Amt Ludwigslust-Land", "str": "Wöbbeliner Straße 5"}, 
{"ags": "13076086", "area": 19.92, "email": null, "gemeinde": "Lübesse", "name": null, "ort": "Ludwigslust", "phone": null, "plz": "19288", "population": 697, "sitz": "Amt Ludwigslust-Land", "str": "Wöbbeliner Straße 5"}, 
{"ags": "13076087", "area": 21.6, "email": null, "gemeinde": "Lüblow", "name": null, "ort": "Ludwigslust", "phone": null, "plz": "19288", "population": 567, "sitz": "Amt Ludwigslust-Land", "str": "Wöbbeliner Straße 5"}, 
{"ags": "13076118", "area": 52.03, "email": null, "gemeinde": "Rastow", "name": null, "ort": "Ludwigslust", "phone": null, "plz": "19288", "population": 1965, "sitz": "Amt Ludwigslust-Land", "str": "Wöbbeliner Straße 5"}, 
{"ags": "13076134", "area": 18.78, "email": null, "gemeinde": "Sülstorf", "name": null, "ort": "Ludwigslust", "phone": null, "plz": "19288", "population": 854, "sitz": "Amt Ludwigslust-Land", "str": "Wöbbeliner Straße 5"}, 
{"ags": "13076141", "area": 15.09, "email": null, "gemeinde": "Uelitz", "name": null, "ort": "Ludwigslust", "phone": null, "plz": "19288", "population": 485, "sitz": "Amt Ludwigslust-Land", "str": "Wöbbeliner Straße 5"}, 
{"ags": "13076146", "area": 13.91, "email": null, "gemeinde": "Warlow", "name": null, "ort": "Ludwigslust", "phone": null, "plz": "19288", "population": 508, "sitz": "Amt Ludwigslust-Land", "str": "Wöbbeliner Straße 5"}, 
{"ags": "13076156", "area": 23.51, "email": null, "gemeinde": "Wöbbelin", "name": null, "ort": "Ludwigslust", "phone": null, "plz": "19288", "population": 937, "sitz": "Amt Ludwigslust-Land", "str": "Wöbbeliner Straße 5"}, 
{"ags": "13076108", "area": 124.81, "email": null, "gemeinde": "Parchim, Stadt", "name": null, "ort": "Parchim", "phone": null, "plz": "19370", "population": 17467, "sitz": "Stadt Parchim", "str": "Schuhmarkt 1"}, 
{"ags": "13076035", "area": 40.25, "email": null, "gemeinde": "Domsühl", "name": null, "ort": "Parchim", "phone": null, "plz": "19370", "population": 1350, "sitz": "Amt Parchimer Umland", "str": "Walter-Hase-Straße 42"}, 
{"ags": "13076056", "area": 15.42, "email": null, "gemeinde": "Groß Godems", "name": null, "ort": "Parchim", "phone": null, "plz": "19370", "population": 400, "sitz": "Amt Parchimer Umland", "str": "Walter-Hase-Straße 42"}, 
{"ags": "13076068", "area": 26.46, "email": null, "gemeinde": "Karrenzin", "name": null, "ort": "Parchim", "phone": null, "plz": "19370", "population": 546, "sitz": "Amt Parchimer Umland", "str": "Walter-Hase-Straße 42"}, 
{"ags": "13076085", "area": 46.76, "email": null, "gemeinde": "Lewitzrand", "name": null, "ort": "Parchim", "phone": null, "plz": "19370", "population": 1370, "sitz": "Amt Parchimer Umland", "str": "Walter-Hase-Straße 42"}, 
{"ags": "13076120", "area": 33.71, "email": null, "gemeinde": "Rom", "name": null, "ort": "Parchim", "phone": null, "plz": "19370", "population": 813, "sitz": "Amt Parchimer Umland", "str": "Walter-Hase-Straße 42"}, 
{"ags": "13076126", "area": 49.13, "email": null, "gemeinde": "Spornitz", "name": null, "ort": "Parchim", "phone": null, "plz": "19370", "population": 1220, "sitz": "Amt Parchimer Umland", "str": "Walter-Hase-Straße 42"}, 
{"ags": "13076129", "area": 20.6, "email": null, "gemeinde": "Stolpe", "name": null, "ort": "Parchim", "phone": null, "plz": "19370", "population": 326, "sitz": "Amt Parchimer Umland", "str": "Walter-Hase-Straße 42"}, 
{"ags": "13076160", "area": 36.78, "email": null, "gemeinde": "Ziegendorf", "name": null, "ort": "Parchim", "phone": null, "plz": "19370", "population": 629, "sitz": "Amt Parchimer Umland", "str": "Walter-Hase-Straße 42"}, 
{"ags": "13076162", "area": 38.91, "email": null, "gemeinde": "Zölkow", "name": null, "ort": "Parchim", "phone": null, "plz": "19370", "population": 752, "sitz": "Amt Parchimer Umland", "str": "Walter-Hase-Straße 42"}, 
{"ags": "13076164", "area": 46.7, "email": null, "gemeinde": "Obere Warnow", "name": null, "ort": "Parchim", "phone": null, "plz": "19370", "population": 809, "sitz": "Amt Parchimer Umland", "str": "Walter-Hase-Straße 42"}, 
{"ags": "13076034", "area": 60.57, "email": null, "gemeinde": "Dömitz, Stadt", "name": null, "ort": "Dömitz", "phone": null, "plz": "19303", "population": 2991, "sitz": "Amt Dömitz-Malliß", "str": "Goethestraße 21"}, 
{"ags": "13076053", "area": 31.27, "email": null, "gemeinde": "Grebs-Niendorf", "name": null, "ort": "Dömitz", "phone": null, "plz": "19303", "population": 539, "sitz": "Amt Dömitz-Malliß", "str": "Goethestraße 21"}, 
{"ags": "13076067", "area": 6.88, "email": null, "gemeinde": "Karenz", "name": null, "ort": "Dömitz", "phone": null, "plz": "19303", "population": 219, "sitz": "Amt Dömitz-Malliß", "str": "Goethestraße 21"}, 
{"ags": "13076093", "area": 22.57, "email": null, "gemeinde": "Malk Göhren", "name": null, "ort": "Dömitz", "phone": null, "plz": "19303", "population": 398, "sitz": "Amt Dömitz-Malliß", "str": "Goethestraße 21"}, 
{"ags": "13076094", "area": 25.27, "email": null, "gemeinde": "Malliß", "name": null, "ort": "Dömitz", "phone": null, "plz": "19303", "population": 1088, "sitz": "Amt Dömitz-Malliß", "str": "Goethestraße 21"}, 
{"ags": "13076103", "area": 34.2, "email": null, "gemeinde": "Neu Kaliß", "name": null, "ort": "Dömitz", "phone": null, "plz": "19303", "population": 1930, "sitz": "Amt Dömitz-Malliß", "str": "Goethestraße 21"}, 
{"ags": "13076143", "area": 77.57, "email": null, "gemeinde": "Vielank", "name": null, "ort": "Dömitz", "phone": null, "plz": "19303", "population": 1289, "sitz": "Amt Dömitz-Malliß", "str": "Goethestraße 21"}, 
{"ags": "13076040", "area": 29.72, "email": null, "gemeinde": "Gallin-Kuppentin", "name": null, "ort": "Lübz", "phone": null, "plz": "19386", "population": 462, "sitz": "Amt Eldenburg Lübz", "str": "Am Markt 22"}, 
{"ags": "13076051", "area": 22.8, "email": null, "gemeinde": "Granzin", "name": null, "ort": "Lübz", "phone": null, "plz": "19386", "population": 388, "sitz": "Amt Eldenburg Lübz", "str": "Am Markt 22"}, 
{"ags": "13076075", "area": 24.9, "email": null, "gemeinde": "Kreien", "name": null, "ort": "Lübz", "phone": null, "plz": "19386", "population": 370, "sitz": "Amt Eldenburg Lübz", "str": "Am Markt 22"}, 
{"ags": "13076077", "area": 25.13, "email": null, "gemeinde": "Kritzow", "name": null, "ort": "Lübz", "phone": null, "plz": "19386", "population": 469, "sitz": "Amt Eldenburg Lübz", "str": "Am Markt 22"}, 
{"ags": "13076089", "area": 74.69, "email": null, "gemeinde": "Lübz, Stadt", "name": null, "ort": "Lübz", "phone": null, "plz": "19386", "population": 6167, "sitz": "Amt Eldenburg Lübz", "str": "Am Markt 22"}, 
{"ags": "13076109", "area": 24.81, "email": null, "gemeinde": "Passow", "name": null, "ort": "Lübz", "phone": null, "plz": "19386", "population": 699, "sitz": "Amt Eldenburg Lübz", "str": "Am Markt 22"}, 
{"ags": "13076125", "area": 55.57, "email": null, "gemeinde": "Siggelkow", "name": null, "ort": "Lübz", "phone": null, "plz": "19386", "population": 843, "sitz": "Amt Eldenburg Lübz", "str": "Am Markt 22"}, 
{"ags": "13076151", "area": 18.17, "email": null, "gemeinde": "Werder", "name": null, "ort": "Lübz", "phone": null, "plz": "19386", "population": 347, "sitz": "Amt Eldenburg Lübz", "str": "Am Markt 22"}, 
{"ags": "13076165", "area": 33.19, "email": null, "gemeinde": "Gehlsbach", "name": null, "ort": "Lübz", "phone": null, "plz": "19386", "population": 521, "sitz": "Amt Eldenburg Lübz", "str": "Am Markt 22"}, 
{"ags": "13076168", "area": 94.55, "email": null, "gemeinde": "Ruhner Berge", "name": null, "ort": "Lübz", "phone": null, "plz": "19386", "population": 1889, "sitz": "Amt Eldenburg Lübz", "str": "Am Markt 22"}, 
{"ags": "13076032", "area": 59.25, "email": null, "gemeinde": "Dobbertin", "name": null, "ort": "Goldberg", "phone": null, "plz": "19399", "population": 1093, "sitz": "Amt Goldberg-Mildenitz", "str": "Lange Straße 67"}, 
{"ags": "13076048", "area": 64.72, "email": null, "gemeinde": "Goldberg, Stadt", "name": null, "ort": "Goldberg", "phone": null, "plz": "19399", "population": 3368, "sitz": "Amt Goldberg-Mildenitz", "str": "Lange Straße 67"}, 
{"ags": "13076096", "area": 32.8, "email": null, "gemeinde": "Mestlin", "name": null, "ort": "Goldberg", "phone": null, "plz": "19399", "population": 723, "sitz": "Amt Goldberg-Mildenitz", "str": "Lange Straße 67"}, 
{"ags": "13076104", "area": 47.38, "email": null, "gemeinde": "Neu Poserin", "name": null, "ort": "Goldberg", "phone": null, "plz": "19399", "population": 494, "sitz": "Amt Goldberg-Mildenitz", "str": "Lange Straße 67"}, 
{"ags": "13076135", "area": 41.72, "email": null, "gemeinde": "Techentin", "name": null, "ort": "Goldberg", "phone": null, "plz": "19399", "population": 731, "sitz": "Amt Goldberg-Mildenitz", "str": "Lange Straße 67"}, 
{"ags": "13076003", "area": 12.83, "email": null, "gemeinde": "Balow", "name": null, "ort": "Grabow", "phone": null, "plz": "19300", "population": 314, "sitz": "Amt Grabow", "str": "Am Markt 1"}, 
{"ags": "13076021", "area": 21.4, "email": null, "gemeinde": "Brunow", "name": null, "ort": "Grabow", "phone": null, "plz": "19300", "population": 308, "sitz": "Amt Grabow", "str": "Am Markt 1"}, 
{"ags": "13076027", "area": 17.39, "email": null, "gemeinde": "Dambeck", "name": null, "ort": "Grabow", "phone": null, "plz": "19300", "population": 274, "sitz": "Amt Grabow", "str": "Am Markt 1"}, 
{"ags": "13076037", "area": 34.21, "email": null, "gemeinde": "Eldena", "name": null, "ort": "Grabow", "phone": null, "plz": "19300", "population": 1137, "sitz": "Amt Grabow", "str": "Am Markt 1"}, 
{"ags": "13076049", "area": 53.22, "email": null, "gemeinde": "Gorlosen", "name": null, "ort": "Grabow", "phone": null, "plz": "19300", "population": 460, "sitz": "Amt Grabow", "str": "Am Markt 1"}, 
{"ags": "13076050", "area": 72.27, "email": null, "gemeinde": "Grabow, Stadt", "name": null, "ort": "Grabow", "phone": null, "plz": "19300", "population": 5500, "sitz": "Amt Grabow", "str": "Am Markt 1"}, 
{"ags": "13076069", "area": 19.79, "email": null, "gemeinde": "Karstädt", "name": null, "ort": "Grabow", "phone": null, "plz": "19300", "population": 599, "sitz": "Amt Grabow", "str": "Am Markt 1"}, 
{"ags": "13076076", "area": 16.91, "email": null, "gemeinde": "Kremmin", "name": null, "ort": "Grabow", "phone": null, "plz": "19300", "population": 242, "sitz": "Amt Grabow", "str": "Am Markt 1"}, 
{"ags": "13076097", "area": 33.65, "email": null, "gemeinde": "Milow", "name": null, "ort": "Grabow", "phone": null, "plz": "19300", "population": 357, "sitz": "Amt Grabow", "str": "Am Markt 1"}, 
{"ags": "13076098", "area": 19.3, "email": null, "gemeinde": "Möllenbeck", "name": null, "ort": "Grabow", "phone": null, "plz": "19300", "population": 187, "sitz": "Amt Grabow", "str": "Am Markt 1"}, 
{"ags": "13076100", "area": 19.39, "email": null, "gemeinde": "Muchow", "name": null, "ort": "Grabow", "phone": null, "plz": "19300", "population": 271, "sitz": "Amt Grabow", "str": "Am Markt 1"}, 
{"ags": "13076115", "area": 29.3, "email": null, "gemeinde": "Prislich", "name": null, "ort": "Grabow", "phone": null, "plz": "19300", "population": 681, "sitz": "Amt Grabow", "str": "Am Markt 1"}, 
{"ags": "13076161", "area": 13.33, "email": null, "gemeinde": "Zierzow", "name": null, "ort": "Grabow", "phone": null, "plz": "19300", "population": 372, "sitz": "Amt Grabow", "str": "Am Markt 1"}, 
{"ags": "13076012", "area": 21.6, "email": null, "gemeinde": "Blievenstorf", "name": null, "ort": "Neustadt-Glewe", "phone": null, "plz": "19306", "population": 432, "sitz": "Amt Neustadt-Glewe", "str": "Markt 1"}, 
{"ags": "13076017", "area": 12.52, "email": null, "gemeinde": "Brenz", "name": null, "ort": "Neustadt-Glewe", "phone": null, "plz": "19306", "population": 492, "sitz": "Amt Neustadt-Glewe", "str": "Markt 1"}, 
{"ags": "13076105", "area": 94.12, "email": null, "gemeinde": "Neustadt-Glewe, Stadt", "name": null, "ort": "Neustadt-Glewe", "phone": null, "plz": "19306", "population": 6969, "sitz": "Amt Neustadt-Glewe", "str": "Markt 1"}, 
{"ags": "13076006", "area": 30.39, "email": null, "gemeinde": "Barkhagen", "name": null, "ort": "Plau am See", "phone": null, "plz": "19395", "population": 604, "sitz": "Amt Plau am See", "str": "Markt 2"}, 
{"ags": "13076114", "area": 116.27, "email": null, "gemeinde": "Plau am See, Stadt", "name": null, "ort": "Plau am See", "phone": null, "plz": "19395", "population": 6091, "sitz": "Amt Plau am See", "str": "Markt 2"}, 
{"ags": "13076166", "area": 87.94, "email": null, "gemeinde": "Ganzlin", "name": null, "ort": "Plau am See", "phone": null, "plz": "19395", "population": 1404, "sitz": "Amt Plau am See", "str": "Markt 2"}, 
{"ags": "13076011", "area": 21.42, "email": null, "gemeinde": "Blankenberg", "name": null, "ort": "Sternberg", "phone": null, "plz": "19406", "population": 383, "sitz": "Amt Sternberger Seenlandschaft", "str": "Am Markt 1"}, 
{"ags": "13076015", "area": 28.08, "email": null, "gemeinde": "Borkow", "name": null, "ort": "Sternberg", "phone": null, "plz": "19406", "population": 435, "sitz": "Amt Sternberger Seenlandschaft", "str": "Am Markt 1"}, 
{"ags": "13076020", "area": 27.21, "email": null, "gemeinde": "Brüel, Stadt", "name": null, "ort": "Sternberg", "phone": null, "plz": "19406", "population": 2602, "sitz": "Amt Sternberger Seenlandschaft", "str": "Am Markt 1"}, 
{"ags": "13076026", "area": 24.77, "email": null, "gemeinde": "Dabel", "name": null, "ort": "Sternberg", "phone": null, "plz": "19406", "population": 1389, "sitz": "Amt Sternberger Seenlandschaft", "str": "Am Markt 1"}, 
{"ags": "13076062", "area": 23.7, "email": null, "gemeinde": "Hohen Pritz", "name": null, "ort": "Sternberg", "phone": null, "plz": "19406", "population": 367, "sitz": "Amt Sternberger Seenlandschaft", "str": "Am Markt 1"}, 
{"ags": "13076072", "area": 37.47, "email": null, "gemeinde": "Kobrow", "name": null, "ort": "Sternberg", "phone": null, "plz": "19406", "population": 408, "sitz": "Amt Sternberger Seenlandschaft", "str": "Am Markt 1"}, 
{"ags": "13076078", "area": 49.92, "email": null, "gemeinde": "Kuhlen-Wendorf", "name": null, "ort": "Sternberg", "phone": null, "plz": "19406", "population": 807, "sitz": "Amt Sternberger Seenlandschaft", "str": "Am Markt 1"}, 
{"ags": "13076101", "area": 26.19, "email": null, "gemeinde": "Mustin", "name": null, "ort": "Sternberg", "phone": null, "plz": "19406", "population": 355, "sitz": "Amt Sternberger Seenlandschaft", "str": "Am Markt 1"}, 
{"ags": "13076128", "area": 67.7, "email": null, "gemeinde": "Sternberg, Stadt", "name": null, "ort": "Sternberg", "phone": null, "plz": "19406", "population": 4031, "sitz": "Amt Sternberger Seenlandschaft", "str": "Am Markt 1"}, 
{"ags": "13076148", "area": 42.21, "email": null, "gemeinde": "Weitendorf", "name": null, "ort": "Sternberg", "phone": null, "plz": "19406", "population": 368, "sitz": "Amt Sternberger Seenlandschaft", "str": "Am Markt 1"}, 
{"ags": "13076155", "area": 18.79, "email": null, "gemeinde": "Witzin", "name": null, "ort": "Sternberg", "phone": null, "plz": "19406", "population": 464, "sitz": "Amt Sternberger Seenlandschaft", "str": "Am Markt 1"}, 
{"ags": "13076167", "area": 24.95, "email": null, "gemeinde": "Kloster Tempzin", "name": null, "ort": "Sternberg", "phone": null, "plz": "19406", "population": 550, "sitz": "Amt Sternberger Seenlandschaft", "str": "Am Markt 1"}, 
{"ags": "13076036", "area": 31.52, "email": null, "gemeinde": "Dümmer", "name": null, "ort": "Stralendorf", "phone": null, "plz": "19073", "population": 1543, "sitz": "Amt Stralendorf", "str": "Dorfstraße 30"}, 
{"ags": "13076063", "area": 20.56, "email": null, "gemeinde": "Holthusen", "name": null, "ort": "Stralendorf", "phone": null, "plz": "19073", "population": 944, "sitz": "Amt Stralendorf", "str": "Dorfstraße 30"}, 
{"ags": "13076071", "area": 11.04, "email": null, "gemeinde": "Klein Rogahn", "name": null, "ort": "Stralendorf", "phone": null, "plz": "19073", "population": 1326, "sitz": "Amt Stralendorf", "str": "Dorfstraße 30"}, 
{"ags": "13076107", "area": 11.01, "email": null, "gemeinde": "Pampow", "name": null, "ort": "Stralendorf", "phone": null, "plz": "19073", "population": 3049, "sitz": "Amt Stralendorf", "str": "Dorfstraße 30"}, 
{"ags": "13076121", "area": 11.42, "email": null, "gemeinde": "Schossin", "name": null, "ort": "Stralendorf", "phone": null, "plz": "19073", "population": 246, "sitz": "Amt Stralendorf", "str": "Dorfstraße 30"}, 
{"ags": "13076130", "area": 12.03, "email": null, "gemeinde": "Stralendorf", "name": null, "ort": "Stralendorf", "phone": null, "plz": "19073", "population": 1381, "sitz": "Amt Stralendorf", "str": "Dorfstraße 30"}, 
{"ags": "13076147", "area": 14.94, "email": null, "gemeinde": "Warsow", "name": null, "ort": "Stralendorf", "phone": null, "plz": "19073", "population": 663, "sitz": "Amt Stralendorf", "str": "Dorfstraße 30"}, 
{"ags": "13076154", "area": 12.28, "email": null, "gemeinde": "Wittenförden", "name": null, "ort": "Stralendorf", "phone": null, "plz": "19073", "population": 2502, "sitz": "Amt Stralendorf", "str": "Dorfstraße 30"}, 
{"ags": "13076163", "area": 7.13, "email": null, "gemeinde": "Zülow", "name": null, "ort": "Stralendorf", "phone": null, "plz": "19073", "population": 139, "sitz": "Amt Stralendorf", "str": "Dorfstraße 30"}, 
{"ags": "13076152", "area": 80.08, "email": null, "gemeinde": "Wittenburg, Stadt", "name": null, "ort": "Wittenburg", "phone": null, "plz": "19243", "population": 6355, "sitz": "Amt Wittenburg", "str": "Molkereistraße 4"}, 
{"ags": "13076153", "area": 104.73, "email": null, "gemeinde": "Wittendörp", "name": null, "ort": "Wittenburg", "phone": null, "plz": "19243", "population": 2892, "sitz": "Amt Wittenburg", "str": "Molkereistraße 4"}, 
{"ags": "13076039", "area": 22.71, "email": null, "gemeinde": "Gallin", "name": null, "ort": "Zarrentin am Schaalsee", "phone": null, "plz": "19246", "population": 576, "sitz": "Amt Zarrentin", "str": "Kirchplatz 8"}, 
{"ags": "13076073", "area": 29.94, "email": null, "gemeinde": "Kogel", "name": null, "ort": "Zarrentin am Schaalsee", "phone": null, "plz": "19246", "population": 648, "sitz": "Amt Zarrentin", "str": "Kirchplatz 8"}, 
{"ags": "13076092", "area": 24.54, "email": null, "gemeinde": "Lüttow-Valluhn", "name": null, "ort": "Zarrentin am Schaalsee", "phone": null, "plz": "19246", "population": 872, "sitz": "Amt Zarrentin", "str": "Kirchplatz 8"}, 
{"ags": "13076142", "area": 106.7, "email": null, "gemeinde": "Vellahn", "name": null, "ort": "Zarrentin am Schaalsee", "phone": null, "plz": "19246", "population": 2771, "sitz": "Amt Zarrentin", "str": "Kirchplatz 8"}, 
{"ags": "13076159", "area": 91.9, "email": null, "gemeinde": "Zarrentin am Schaalsee, Stadt", "name": null, "ort": "Zarrentin am Schaalsee", "phone": null, "plz": "19246", "population": 5421, "sitz": "Amt Zarrentin", "str": "Kirchplatz 8"}, 
{"ags": "13076005", "area": 52.59, "email": null, "gemeinde": "Banzkow", "name": null, "ort": "Crivitz", "phone": null, "plz": "19089", "population": 2797, "sitz": "Crivitz", "str": "Amtsstraße 5"}, 
{"ags": "13076007", "area": 17.02, "email": null, "gemeinde": "Barnin", "name": null, "ort": "Crivitz", "phone": null, "plz": "19089", "population": 473, "sitz": "Crivitz", "str": "Amtsstraße 5"}, 
{"ags": "13076023", "area": 23.85, "email": null, "gemeinde": "Bülow", "name": null, "ort": "Crivitz", "phone": null, "plz": "19089", "population": 335, "sitz": "Crivitz", "str": "Amtsstraße 5"}, 
{"ags": "13076024", "area": 20.78, "email": null, "gemeinde": "Cambs", "name": null, "ort": "Crivitz", "phone": null, "plz": "19089", "population": 628, "sitz": "Crivitz", "str": "Amtsstraße 5"}, 
{"ags": "13076025", "area": 75.85, "email": null, "gemeinde": "Crivitz, Stadt", "name": null, "ort": "Crivitz", "phone": null, "plz": "19089", "population": 4770, "sitz": "Crivitz", "str": "Amtsstraße 5"}, 
{"ags": "13076029", "area": 46.82, "email": null, "gemeinde": "Demen", "name": null, "ort": "Crivitz", "phone": null, "plz": "19089", "population": 846, "sitz": "Crivitz", "str": "Amtsstraße 5"}, 
{"ags": "13076033", "area": 35.03, "email": null, "gemeinde": "Dobin am See", "name": null, "ort": "Crivitz", "phone": null, "plz": "19089", "population": 1998, "sitz": "Crivitz", "str": "Amtsstraße 5"}, 
{"ags": "13076038", "area": 34.67, "email": null, "gemeinde": "Friedrichsruhe", "name": null, "ort": "Crivitz", "phone": null, "plz": "19089", "population": 908, "sitz": "Crivitz", "str": "Amtsstraße 5"}, 
{"ags": "13076044", "area": 10.41, "email": null, "gemeinde": "Gneven", "name": null, "ort": "Crivitz", "phone": null, "plz": "19089", "population": 376, "sitz": "Crivitz", "str": "Amtsstraße 5"}, 
{"ags": "13076080", "area": 15.43, "email": null, "gemeinde": "Langen Brütz", "name": null, "ort": "Crivitz", "phone": null, "plz": "19089", "population": 495, "sitz": "Crivitz", "str": "Amtsstraße 5"}, 
{"ags": "13076082", "area": 26.53, "email": null, "gemeinde": "Leezen", "name": null, "ort": "Crivitz", "phone": null, "plz": "19089", "population": 2207, "sitz": "Crivitz", "str": "Amtsstraße 5"}, 
{"ags": "13076112", "area": 18.75, "email": null, "gemeinde": "Pinnow", "name": null, "ort": "Crivitz", "phone": null, "plz": "19089", "population": 2025, "sitz": "Crivitz", "str": "Amtsstraße 5"}, 
{"ags": "13076113", "area": 22.13, "email": null, "gemeinde": "Plate", "name": null, "ort": "Crivitz", "phone": null, "plz": "19089", "population": 3312, "sitz": "Crivitz", "str": "Amtsstraße 5"}, 
{"ags": "13076117", "area": 9.6, "email": null, "gemeinde": "Raben Steinfeld", "name": null, "ort": "Crivitz", "phone": null, "plz": "19089", "population": 1062, "sitz": "Crivitz", "str": "Amtsstraße 5"}, 
{"ags": "13076133", "area": 21.36, "email": null, "gemeinde": "Sukow", "name": null, "ort": "Crivitz", "phone": null, "plz": "19089", "population": 1521, "sitz": "Crivitz", "str": "Amtsstraße 5"}, 
{"ags": "13076140", "area": 42.13, "email": null, "gemeinde": "Tramm", "name": null, "ort": "Crivitz", "phone": null, "plz": "19089", "population": 905, "sitz": "Crivitz", "str": "Amtsstraße 5"}, 
{"ags": "13076158", "area": 11.63, "email": null, "gemeinde": "Zapel", "name": null, "ort": "Crivitz", "phone": null, "plz": "19089", "population": 438, "sitz": "Crivitz", "str": "Amtsstraße 5"}]