{"25335": ["Altenmoor", "Altenmoor (Schleswig-Holstein)", "Bokholt-Hanredder", "Bokholt-Hanredder (Schleswig-Holstein)", "Elmshorn", "Elmshorn (Schleswig-Holstein)", "Neuendorf", "Neuendorf (Schleswig-Holstein)", "Neuendorf b. Elmshorn", "Raa-Besenbek", "Raa-Besenbek (Schleswig-Holstein)"], 
"25336": ["Elmshorn", "Klein Nordende", "Klein Nordende (Schleswig-Holstein)"], 
"25337": ["Elmshorn", "K\u00f6lln-Reisiek", "K\u00f6lln-Reisiek (Schleswig-Holstein)", "Seeth-Ekholt", "Seeth-Ekholt (Schleswig-Holstein)"], 
"25348": ["Blomesche Wildnis", "Blomesche Wildnis (Schleswig-Holstein)", "Engelbrechtsche Wildnis", "Engelbrechtsche Wildnis (Schleswig-Holstein)", "Gl\u00fcckstadt", "Gl\u00fcckstadt (Schleswig-Holstein)"], 
"25355": ["Barmstedt", "Barmstedt (Schleswig-Holstein)", "Bevern", "Bevern (Schleswig-Holstein)", "Bullenkuhlen", "Bullenkuhlen (Schleswig-Holstein)", "Gro\u00df Offenseth-Aspern", "Gro\u00df Offenseth-Aspern (Schleswig-Holstein)", "Heede", "Heede (Schleswig-Holstein)", "Lutzhorn", "Lutzhorn (Schleswig-Holstein)"], 
"25358": ["Dauenhof", "Glindesmoor", "Halenbrook", "Hohenfelde", "Hohenfelde (Schleswig-Holstein)", "Horst", "Horst (Holstein)", "Horst (Schleswig-Holstein)", "Niederreihe", "Oberreihe", "Sommerland", "Sommerland (Schleswig-Holstein)"], 
"25361": ["Elskop", "Elskop (Schleswig-Holstein)", "Gehrhof", "Grevenkop", "Grevenkop (Schleswig-Holstein)", "Krempdorf", "Krempdorf (Schleswig-Holstein)", "Krempe", "Krempe (Schleswig-Holstein)", "Muchelndorf", "Neuenbrook", "Neuenbrook (Schleswig-Holstein)", "S\u00fcderau", "S\u00fcderau (Schleswig-Holstein)"], 
"25364": ["Bokel", "Bokel (Schleswig-Holstein)", "Brande-H\u00f6rnerkirchen", "Brande-H\u00f6rnerkirchen (Schleswig-Holstein)", "Osterhorn", "Osterhorn (Schleswig-Holstein)", "Westerhorn", "Westerhorn (Schleswig-Holstein)"], 
"25365": ["Klein Offenseth-Sparrieshoop", "Klein Offenseth-Sparrieshoop (Schleswig-Holstein)"], 
"25368": ["Kiebitzreihe", "Kiebitzreihe (Schleswig-Holstein)"], 
"25370": ["Seester", "Seester (Schleswig-Holstein)"], 
"25371": ["Seesterm\u00fche", "Seesterm\u00fche (Schleswig-Holstein)"], 
"25373": ["Ellerhoop", "Ellerhoop (Schleswig-Holstein)"], 
"25376": ["Borsfleth", "Borsfleth (Schleswig-Holstein)", "Krempdorf"], 
"25377": ["Kollmar", "Kollmar (Schleswig-Holstein)", "Pagensand"], 
"25379": ["Herzhorn", "Herzhorn (Schleswig-Holstein)", "Kamerlanderdeich"], 
"25421": ["Pinneberg", "Pinneberg (Schleswig-Holstein)", "Waldenau-Datum"], 
"25436": ["Gro\u00df Nordende", "Gro\u00df Nordende (Schleswig-Holstein)", "Heidgraben", "Heidgraben (Schleswig-Holstein)", "Moorrege", "Moorrege (Schleswig-Holstein)", "Neuendeich", "Neuendeich (Schleswig-Holstein)", "Tornesch", "Tornesch (Schleswig-Holstein)", "Uetersen", "Uetersen (Schleswig-Holstein)"], 
"25451": ["Quickborn", "Quickborn (Schleswig-Holstein)", "Quickborn-Heide"], 
"25462": ["Rellingen", "Rellingen (Schleswig-Holstein)"], 
"25469": ["Halstenbek", "Halstenbek (Schleswig-Holstein)"], 
"25474": ["B\u00f6nningstedt", "B\u00f6nningstedt (Schleswig-Holstein)", "Ellerbek", "Ellerbek (Schleswig-Holstein)", "Hasloh", "Hasloh (Schleswig-Holstein)"], 
"25479": ["Ellerau", "Ellerau (Schleswig-Holstein)"], 
"25482": ["Appen", "Appen (Schleswig-Holstein)"], 
"25485": ["Bilsen", "Bilsen (Schleswig-Holstein)", "Hemdingen", "Hemdingen (Schleswig-Holstein)", "Langeln", "Langeln (Schleswig-Holstein)"], 
"25486": ["Alveslohe", "Alveslohe (Schleswig-Holstein)"], 
"25488": ["Holm", "Holm (Schleswig-Holstein)"], 
"25489": ["Haselau", "Haselau (Schleswig-Holstein)", "Haseldorf", "Haseldorf (Schleswig-Holstein)"], 
"25491": ["Hetlingen", "Hetlingen (Schleswig-Holstein)"], 
"25492": ["Heist", "Heist (Schleswig-Holstein)", "Hetlinger Neuerkoog"], 
"25494": ["Borstel-Hohenraden", "Borstel-Hohenraden (Schleswig-Holstein)"], 
"25495": ["Kummerfeld", "Kummerfeld (Schleswig-Holstein)"], 
"25497": ["Prisdorf", "Prisdorf (Schleswig-Holstein)"], 
"25499": ["Tangstedt", "Tangstedt (Schleswig-Holstein)"], 
"25524": ["Bekm\u00fcnde", "Bekm\u00fcnde (Schleswig-Holstein)", "Breitenburg", "Breitenburg (Schleswig-Holstein)", "Heiligenstedten", "Heiligenstedten (Schleswig-Holstein)", "Heiligenstedtenerkamp", "Heiligenstedtenerkamp (Schleswig-Holstein)", "Itzehoe", "Itzehoe (Schleswig-Holstein)", "Kollmoor", "Kollmoor (Schleswig-Holstein)", "Oelixdorf", "Oelixdorf (Schleswig-Holstein)"], 
"25541": ["Brunsb\u00fcttel", "Brunsb\u00fcttel (Schleswig-Holstein)"], 
"25548": ["Auufer", "Auufer (Schleswig-Holstein)", "Kellinghusen", "Kellinghusen (Schleswig-Holstein)", "M\u00fchlenbarbek", "M\u00fchlenbarbek (Schleswig-Holstein)", "Oescheb\u00fcttel", "Oescheb\u00fcttel (Schleswig-Holstein)", "Rosdorf", "Rosdorf (Schleswig-Holstein)", "St\u00f6rkathen", "St\u00f6rkathen (Schleswig-Holstein)", "Wittenbergen", "Wittenbergen (Schleswig-Holstein)"], 
"25551": ["Hohenlockstedt", "Hohenlockstedt (Schleswig-Holstein)", "Lockstedt", "Lockstedt (Schleswig-Holstein)", "Lohbarbek", "Lohbarbek (Schleswig-Holstein)", "Peissen", "Peissen (Schleswig-Holstein)", "Schlotfeld", "Schlotfeld (Schleswig-Holstein)", "Silzen", "Silzen (Schleswig-Holstein)", "Springhoe", "Winseldorf", "Winseldorf (Schleswig-Holstein)"], 
"25554": ["Bekdorf", "Bekdorf (Schleswig-Holstein)", "Brokdorf", "Brokdorf (Schleswig-Holstein)", "Brokdorferlandscheide", "Dammfleth", "Dammfleth (Schleswig-Holstein)", "Kleve", "Kleve (Schleswig-Holstein)", "Krummendiek", "Krummendiek (Schleswig-Holstein)", "Landrecht", "Landrecht (Schleswig-Holstein)", "Moorhusen", "Moorhusen (Schleswig-Holstein)", "Neuendorf-Sachsenbande", "Neuendorf-Sachsenbande (Schleswig-Holstein)", "Nortorf", "Nortorf (Schleswig-Holstein)", "St\u00f6rdorf", "St\u00f6rdorf (Schleswig-Holstein)", "Wilster", "Wilster (Schleswig-Holstein)"], 
"25557": ["Beldorf", "Beldorf (Schleswig-Holstein)", "Bendorf", "Bendorf (Schleswig-Holstein)", "Bornholt", "Bornholt (Schleswig-Holstein)", "Gokels", "Gokels (Schleswig-Holstein)", "Hanerau-Hademarschen", "Hanerau-Hademarschen (Schleswig-Holstein)", "Keller", "Oldenb\u00fcttel", "Oldenb\u00fcttel (Schleswig-Holstein)", "Seefeld", "Seefeld (Schleswig-Holstein)", "Steenfeld", "Steenfeld (Schleswig-Holstein)", "Thaden", "Thaden (Schleswig-Holstein)"], 
"25560": ["Aasb\u00fcttel", "Aasb\u00fcttel (Schleswig-Holstein)", "Agethorst", "Agethorst (Schleswig-Holstein)", "Bokhorst", "Bokhorst (Schleswig-Holstein)", "Hadenfeld", "Hadenfeld (Schleswig-Holstein)", "Kaisborstel", "Kaisborstel (Schleswig-Holstein)", "Oldenborstel", "Oldenborstel (Schleswig-Holstein)", "Puls", "Puls (Schleswig-Holstein)", "P\u00f6schendorf", "P\u00f6schendorf (Schleswig-Holstein)", "Schenefeld", "Schenefeld (Schleswig-Holstein)", "Siezb\u00fcttel", "Warringholz", "Warringholz (Schleswig-Holstein)"], 
"25563": ["Bargholz", "F\u00f6hrden-Barl", "F\u00f6hrden-Barl (Schleswig-Holstein)", "Hingstheide", "Hingstheide (Schleswig-Holstein)", "Quarnstedt", "Quarnstedt (Schleswig-Holstein)", "Wrist", "Wrist (Schleswig-Holstein)", "Wulfsmoor", "Wulfsmoor (Schleswig-Holstein)"], 
"25566": ["L\u00e4gerdorf", "L\u00e4gerdorf (Schleswig-Holstein)", "Rethwisch", "Rethwisch (Schleswig-Holstein)"], 
"25569": ["Bahrenfleth", "Bahrenfleth (Schleswig-Holstein)", "Hodorf", "Hodorf (Schleswig-Holstein)", "Kremperheide", "Kremperheide (Schleswig-Holstein)", "Krempermoor", "Krempermoor (Schleswig-Holstein)"], 
"25572": ["Aebtissinwisch", "Aebtissinwisch (Schleswig-Holstein)", "B\u00fcttel", "B\u00fcttel (Schleswig-Holstein)", "Ecklak", "Ecklak (Schleswig-Holstein)", "Kudensee", "Kudensee (Schleswig-Holstein)", "Landscheide", "Landscheide (Schleswig-Holstein)", "Oberstenwehr", "Sankt Margarethen", "Sankt Margarethen (Schleswig-Holstein)", "Vaale", "Vaale (Schleswig-Holstein)", "Vaalerfeld"], 
"25573": ["Beidenfleth", "Beidenfleth (Schleswig-Holstein)", "Klein Kampen"], 
"25575": ["Beringstedt", "Beringstedt (Schleswig-Holstein)"], 
"25576": ["Brokdorf"], 
"25578": ["D\u00e4geling", "D\u00e4geling (Schleswig-Holstein)", "Neuenbrook", "Neuenbrook (Schleswig-Holstein)"], 
"25579": ["Fitzbek", "Fitzbek (Schleswig-Holstein)", "Rade", "Rade (Schleswig-Holstein)"], 
"25581": ["Hennstedt", "Hennstedt (Schleswig-Holstein)", "Poyenberg", "Poyenberg (Schleswig-Holstein)"], 
"25582": ["Drage", "Drage (Schleswig-Holstein)", "Hohenaspe", "Hohenaspe (Schleswig-Holstein)", "Kaaks", "Kaaks (Schleswig-Holstein)", "Looft", "Looft (Schleswig-Holstein)"], 
"25584": ["Besdorf", "Besdorf (Schleswig-Holstein)", "Holstenniendorf", "Holstenniendorf (Schleswig-Holstein)"], 
"25585": ["L\u00fctjenwestedt", "L\u00fctjenwestedt (Schleswig-Holstein)", "Tackesdorf", "Tackesdorf (Schleswig-Holstein)"], 
"25587": ["M\u00fcnsterdorf", "M\u00fcnsterdorf (Schleswig-Holstein)"], 
"25588": ["Huje", "Huje (Schleswig-Holstein)", "Mehlbek", "Mehlbek (Schleswig-Holstein)", "Oldendorf", "Oldendorf (Schleswig-Holstein)"], 
"25590": ["Osterstedt", "Osterstedt (Schleswig-Holstein)"], 
"25591": ["Ottenb\u00fcttel", "Ottenb\u00fcttel (Schleswig-Holstein)"], 
"25593": ["Christinenthal", "Christinenthal (Schleswig-Holstein)", "Reher", "Reher (Schleswig-Holstein)"], 
"25594": ["Nutteln", "Nutteln (Schleswig-Holstein)", "Vaale", "Vaalermoor", "Vaalermoor (Schleswig-Holstein)"], 
"25596": ["Bokelrehm", "Bokelrehm (Schleswig-Holstein)", "Gribbohm", "Gribbohm (Schleswig-Holstein)", "Nienb\u00fcttel", "Nienb\u00fcttel (Schleswig-Holstein)", "Wacken", "Wacken (Schleswig-Holstein)"], 
"25597": ["Breitenberg", "Breitenberg (Schleswig-Holstein)", "Kronsmoor", "Kronsmoor (Schleswig-Holstein)", "Moordiek", "Moordiek (Schleswig-Holstein)", "Westermoor", "Westermoor (Schleswig-Holstein)"], 
"25599": ["Wewelsfleth", "Wewelsfleth (Schleswig-Holstein)"], 
"25693": ["Dithmarschen-Gudendorf", "Dithmarschen-Trennewurth", "Dithmarschen-Volsemenhusen", "Gudendorf", "Sankt Michaelisdonn", "Sankt Michaelisdonn (Dithmarschen)", "St. Michaelisdonn", "Trennewurth", "Volsemenhusen"], 
"25704": ["Bargenstedt", "Bargenstedt (Schleswig-Holstein)", "Elpersb\u00fcttel", "Elpersb\u00fcttel (Schleswig-Holstein)", "Epenw\u00f6hrden", "Epenw\u00f6hrden (Schleswig-Holstein)", "Meldorf", "Meldorf (Schleswig-Holstein)", "Nindorf", "Nindorf (Schleswig-Holstein)", "Nordermeldorf", "Nordermeldorf (Schleswig-Holstein)", "Wolmersdorf", "Wolmersdorf (Schleswig-Holstein)"], 
"25709": ["Diekhusen-Fahrstedt", "Diekhusen-Fahrstedt (Schleswig-Holstein)", "Helse", "Helse (Schleswig-Holstein)", "Kaiser-Wilhelm-Koog", "Kaiser-Wilhelm-Koog (Schleswig-Holstein)", "Kronprinzenkoog", "Kronprinzenkoog (Schleswig-Holstein)", "Marne", "Marne (Schleswig-Holstein)", "Marnerdeich", "Marnerdeich (Schleswig-Holstein)"], 
"25712": ["Brickeln", "Brickeln (Schleswig-Holstein)", "Buchholz", "Buchholz (Schleswig-Holstein)", "Burg", "Burg (Dithmarschen)", "Burg (Schleswig-Holstein)", "Burgerfeld", "Gro\u00dfenrade", "Gro\u00dfenrade (Schleswig-Holstein)", "Hochdonn", "Hochdonn (Schleswig-Holstein)", "Kuden", "Kuden (Schleswig-Holstein)", "Quickborn", "Quickborn (Schleswig-Holstein)"], 
"25715": ["Averlak", "Averlak (Schleswig-Holstein)", "Blangenmoorfeld", "Dingen", "Dingen (Schleswig-Holstein)", "Eddelak", "Eddelak (Schleswig-Holstein)", "Ramhusen", "Ramhusen (Schleswig-Holstein)"], 
"25718": ["Friedrichskoog", "Friedrichskoog (Schleswig-Holstein)"], 
"25719": ["Barlt", "Barlt (Schleswig-Holstein)", "Busenwurth", "Busenwurth (Schleswig-Holstein)"], 
"25721": ["Eggstedt", "Eggstedt (Schleswig-Holstein)"], 
"25724": ["Neufeld", "Neufeld (Schleswig-Holstein)", "Neufelderkoog", "Neufelderkoog (Schleswig-Holstein)", "Schmedeswurth", "Schmedeswurth (Schleswig-Holstein)"], 
"25725": ["Bornholt", "Bornholt (Schleswig-Holstein)", "Schafstedt", "Schafstedt (Schleswig-Holstein)", "Weidenhof"], 
"25727": ["Frestedt", "Frestedt (Schleswig-Holstein)", "Krumstedt", "Krumstedt (Schleswig-Holstein)", "S\u00fcderhastedt", "S\u00fcderhastedt (Schleswig-Holstein)"], 
"25729": ["Windbergen", "Windbergen (Schleswig-Holstein)"], 
"25746": ["Heide", "Heide (Schleswig-Holstein)", "Lohe-Rickelshof", "Lohe-Rickelshof (Schleswig-Holstein)", "Norderw\u00f6hrden", "Norderw\u00f6hrden (Schleswig-Holstein)", "Ostrohe", "Ostrohe (Schleswig-Holstein)", "Wesseln", "Wesseln (Schleswig-Holstein)"], 
"25761": ["B\u00fcsum", "B\u00fcsum (Schleswig-Holstein)", "B\u00fcsumer Deichhausen", "B\u00fcsumer Deichhausen (Schleswig-Holstein)", "Hedwigenkoog", "Hedwigenkoog (Schleswig-Holstein)", "Oesterdeichstrich", "Oesterdeichstrich (Schleswig-Holstein)", "Warwerort", "Warwerort (Schleswig-Holstein)", "Westerdeichstrich", "Westerdeichstrich (Schleswig-Holstein)"], 
"25764": ["Friedrichsgabekoog", "Friedrichsgabekoog (Schleswig-Holstein)", "Hellschen-Heringsand-Unterschaar", "Hellschen-Heringsand-Unterschaar (Schleswig-Holstein)", "Hillgroven", "Hillgroven (Schleswig-Holstein)", "Norddeich", "Norddeich (Schleswig-Holstein)", "Oesterwurth", "Oesterwurth (Schleswig-Holstein)", "Reinsb\u00fcttel", "Reinsb\u00fcttel (Schleswig-Holstein)", "Sch\u00fclp", "Sch\u00fclp (Schleswig-Holstein)", "S\u00fcderdeich", "S\u00fcderdeich (Schleswig-Holstein)", "Wesselburen", "Wesselburen (Schleswig-Holstein)", "Wesselburener Deichhausen", "Wesselburener Deichhausen (Schleswig-Holstein)", "Wesselburenerkoog", "Wesselburenerkoog (Schleswig-Holstein)", "Wulfenhusen"], 
"25767": ["Albersdorf", "Albersdorf (Schleswig-Holstein)", "Arkebek", "Arkebek (Schleswig-Holstein)", "Beldorf", "Beldorf (Schleswig-Holstein)", "Bunsoh", "Bunsoh (Schleswig-Holstein)", "Gr\u00fcnental", "Immenstedt", "Immenstedt (Schleswig-Holstein)", "Offenb\u00fcttel", "Offenb\u00fcttel (Schleswig-Holstein)", "Osterrade", "Osterrade (Schleswig-Holstein)", "Riesewohld", "Tensb\u00fcttel-R\u00f6st", "Tensb\u00fcttel-R\u00f6st (Schleswig-Holstein)", "Wennb\u00fcttel", "Wennb\u00fcttel (Schleswig-Holstein)"], 
"25770": ["Hemmingstedt", "Hemmingstedt (Schleswig-Holstein)", "Lieth", "Lieth (Schleswig-Holstein)"], 
"25774": ["Groven", "Groven (Schleswig-Holstein)", "Hemme", "Hemme (Schleswig-Holstein)", "Karolinenkoog", "Karolinenkoog (Schleswig-Holstein)", "Krempel", "Krempel (Schleswig-Holstein)", "Lehe", "Lehe (Schleswig-Holstein)", "Lunden", "Lunden (Schleswig-Holstein)"], 
"25776": ["Dammsfeld", "Hehm", "Kleve", "Kleve (Schleswig-Holstein)", "Leherfeld", "Nordfeld", "Rehm-Flehde-Bargen", "Rehm-Flehde-Bargen (Schleswig-Holstein)", "Sankt Annen", "Sankt Annen (Schleswig-Holstein)", "St. Annen"], 
"25779": ["Bergew\u00f6hrden", "Bergew\u00f6hrden (Schleswig-Holstein)", "Fedderingen", "Fedderingen (Schleswig-Holstein)", "Gl\u00fcsing", "Gl\u00fcsing (Schleswig-Holstein)", "Hennstedt", "Hennstedt (Schleswig-Holstein)", "H\u00e4gen", "Kleve", "Norderheistedt", "Norderheistedt (Schleswig-Holstein)", "Schlichting", "Schlichting (Schleswig-Holstein)", "S\u00fcderheistedt", "S\u00fcderheistedt (Schleswig-Holstein)", "Westermoor", "Wiemerstedt", "Wiemerstedt (Schleswig-Holstein)"], 
"25782": ["Gaushorn", "Gaushorn (Schleswig-Holstein)", "H\u00f6vede", "H\u00f6vede (Schleswig-Holstein)", "Schalkholz", "Schalkholz (Schleswig-Holstein)", "Schrum", "Schrum (Schleswig-Holstein)", "S\u00fcderdorf", "S\u00fcderdorf (Schleswig-Holstein)", "Tellingstedt", "Tellingstedt (Schleswig-Holstein)", "Welmb\u00fcttel", "Welmb\u00fcttel (Schleswig-Holstein)", "Westerborstel", "Westerborstel (Schleswig-Holstein)"], 
"25785": ["Nordhastedt", "Nordhastedt (Schleswig-Holstein)", "Odderade", "Odderade (Schleswig-Holstein)", "Sarzb\u00fcttel", "Sarzb\u00fcttel (Schleswig-Holstein)", "Westerwohld"], 
"25786": ["Dellstedt", "Dellstedt (Schleswig-Holstein)"], 
"25788": ["Delve", "Delve (Schleswig-Holstein)", "Hollingstedt", "Hollingstedt (Schleswig-Holstein)", "Wallen", "Wallen (Schleswig-Holstein)"], 
"25791": ["Barkenholm", "Barkenholm (Schleswig-Holstein)", "Linden", "Linden (Schleswig-Holstein)"], 
"25792": ["Neuenkirchen", "Neuenkirchen (Schleswig-Holstein)", "Str\u00fcbbel", "Str\u00fcbbel (Schleswig-Holstein)"], 
"25794": ["D\u00f6rpling", "D\u00f6rpling (Schleswig-Holstein)", "Pahlen", "Pahlen (Schleswig-Holstein)", "Tielenhemme", "Tielenhemme (Schleswig-Holstein)"], 
"25795": ["Stelle-Wittenwurth", "Stelle-Wittenwurth (Schleswig-Holstein)", "Weddingstedt", "Weddingstedt (Schleswig-Holstein)"], 
"25797": ["W\u00f6hrden", "W\u00f6hrden (Schleswig-Holstein)"], 
"25799": ["Wrohm", "Wrohm (Schleswig-Holstein)"], 
"25813": ["Husum", "Husum (Schleswig-Holstein)", "Kielsburg", "Schob\u00fcll", "Schwesing", "Schwesing (Schleswig-Holstein)", "Simonsberg", "Simonsberg (Schleswig-Holstein)", "Spaltenhof", "S\u00fcdermarsch", "S\u00fcdermarsch (Schleswig-Holstein)"], 
"25821": ["Almdorf", "Almdorf (Schleswig-Holstein)", "Bordelum", "Bordelum (Schleswig-Holstein)", "Bordelumsiel", "Bredstedt", "Bredstedt (Schleswig-Holstein)", "Breklum", "Breklum (Schleswig-Holstein)", "Brommelund", "Cecilienkoog", "Desmerciereskoog", "D\u00f6rpum", "D\u00f6rpumfeld", "Reu\u00dfenk\u00f6ge", "Reu\u00dfenk\u00f6ge (Schleswig-Holstein)", "Struckum", "Struckum (Schleswig-Holstein)", "S\u00f6nneb\u00fcll", "S\u00f6nneb\u00fcll (Schleswig-Holstein)", "Vollstedt", "Vollstedt (Schleswig-Holstein)"], 
"25826": ["Sankt Peter-Ording", "Sankt Peter-Ording (Schleswig-Holstein)"], 
"25832": ["Kotzenb\u00fcll", "Kotzenb\u00fcll (Schleswig-Holstein)", "T\u00f6nning", "T\u00f6nning (Schleswig-Holstein)"], 
"25836": ["Garding", "Garding (Schleswig-Holstein)", "Garding, Kirchspiel", "Grothusenkoog", "Grothusenkoog (Schleswig-Holstein)", "Katharinenheerd", "Katharinenheerd (Schleswig-Holstein)", "Kirchspiel Garding", "Kirchspiel Garding (Schleswig-Holstein)", "Osterhever", "Osterhever (Schleswig-Holstein)", "Poppenb\u00fcll", "Poppenb\u00fcll (Schleswig-Holstein)", "Vollerwiek", "Vollerwiek (Schleswig-Holstein)", "Welt", "Welt (Schleswig-Holstein)"], 
"25840": ["An der Chaussee", "Drage", "Drage (Schleswig-Holstein)", "Feddersdeich", "Friedrichstadt", "Friedrichstadt (Schleswig-Holstein)", "Hakenhof", "Koldenb\u00fcttel", "Koldenb\u00fcttel (Schleswig-Holstein)", "Mildterhof", "Peterskoogsdeich", "Rantrumdeich", "Seeth", "Seeth (Schleswig-Holstein)", "Ziegelhof"], 
"25842": ["Addeb\u00fcll", "Bargum", "Bargum (Schleswig-Holstein)", "Bongsiel", "Langenhorn", "Langenhorn (Schleswig-Holstein)", "L\u00fctjenholm", "L\u00fctjenholm (Schleswig-Holstein)", "Ockholm", "Ockholm (Schleswig-Holstein)"], 
"25845": ["Elisabeth-Sophien-Koog", "Elisabeth-Sophien-Koog (Schleswig-Holstein)", "Nordstrand", "Nordstrand (Schleswig-Holstein)", "Nordstrandischmoor", "Pellworm", "Pellworm (Schleswig-Holstein)", "S\u00fcdfall"], 
"25849": ["Pellworm", "S\u00fcderoog", "Tammensiel"], 
"25850": ["Behrendorf", "Behrendorf (Schleswig-Holstein)", "Bondelum", "Bondelum (Schleswig-Holstein)"], 
"25852": ["Bordelum"], 
"25853": ["Ahrensh\u00f6ft", "Ahrensh\u00f6ft (Schleswig-Holstein)", "Bohmstedt", "Bohmstedt (Schleswig-Holstein)", "Drelsdorf", "Drelsdorf (Schleswig-Holstein)"], 
"25855": ["Haselund", "Haselund (Schleswig-Holstein)"], 
"25856": ["Hattstedt", "Hattstedt (Schleswig-Holstein)", "Hattstedtermarsch", "Hattstedtermarsch (Schleswig-Holstein)", "Wobbenb\u00fcll", "Wobbenb\u00fcll (Schleswig-Holstein)"], 
"25858": ["H\u00f6gel", "H\u00f6gel (Schleswig-Holstein)"], 
"25859": ["Hallig Hooge", "Hallig Hooge (Schleswig-Holstein)"], 
"25860": ["Arlewatt", "Arlewatt (Schleswig-Holstein)", "Horstedt", "Horstedt (Schleswig-Holstein)", "Olderup", "Olderup (Schleswig-Holstein)"], 
"25862": ["Goldebek", "Goldebek (Schleswig-Holstein)", "Goldelund", "Goldelund (Schleswig-Holstein)", "Joldelund", "Joldelund (Schleswig-Holstein)", "Kolkerheide", "Kolkerheide (Schleswig-Holstein)"], 
"25863": ["Langene\u00df", "Langene\u00df (Schleswig-Holstein)"], 
"25864": ["L\u00f6wenstedt", "L\u00f6wenstedt (Schleswig-Holstein)"], 
"25866": ["Mildstedt", "Mildstedt (Schleswig-Holstein)"], 
"25867": ["Oland"], 
"25868": ["Norderstapel"], 
"25869": ["Gr\u00f6de", "Gr\u00f6de (Schleswig-Holstein)", "Habel"], 
"25870": ["Norderfriedrichskoog", "Norderfriedrichskoog (Schleswig-Holstein)", "Oldenswort", "Oldenswort (Schleswig-Holstein)"], 
"25872": ["Ostenfeld", "Ostenfeld (Husum)", "Ostenfeld (Schleswig-Holstein)", "Wittbek", "Wittbek (Schleswig-Holstein)"], 
"25873": ["Oldersbek", "Oldersbek (Schleswig-Holstein)", "Rantrum", "Rantrum (Schleswig-Holstein)"], 
"25876": ["Fresendelf", "Fresendelf (Schleswig-Holstein)", "Hude", "Hude (Schleswig-Holstein)", "Huderf\u00e4hre", "Ramstedt", "Ramstedt (Schleswig-Holstein)", "Schwabstedt", "Schwabstedt (Schleswig-Holstein)", "S\u00fcderh\u00f6ft", "S\u00fcderh\u00f6ft (Schleswig-Holstein)", "Wisch", "Wisch (Schleswig-Holstein)"], 
"25878": ["Drage", "Seeth"], 
"25879": ["Stapel", "Stapel (Schleswig-Holstein)", "S\u00fcderstapel"], 
"25881": ["Tating", "Tating (Schleswig-Holstein)", "T\u00fcmlauer Koog", "T\u00fcmlauer Koog (Schleswig-Holstein)", "Westerhever", "Westerhever (Schleswig-Holstein)"], 
"25882": ["Tetenb\u00fcll", "Tetenb\u00fcll (Schleswig-Holstein)"], 
"25884": ["Norstedt", "Norstedt (Schleswig-Holstein)", "Sollwitt", "Sollwitt (Schleswig-Holstein)", "Vi\u00f6l", "Vi\u00f6l (Schleswig-Holstein)"], 
"25885": ["Ahrenvi\u00f6l", "Ahrenvi\u00f6l (Schleswig-Holstein)", "Ahrenvi\u00f6lfeld", "Ahrenvi\u00f6lfeld (Schleswig-Holstein)", "Immenstedt", "Immenstedt (Schleswig-Holstein)", "Oster-Ohrstedt", "Oster-Ohrstedt (Schleswig-Holstein)", "Wester-Ohrstedt", "Wester-Ohrstedt (Schleswig-Holstein)"], 
"25887": ["Winnert", "Winnert (Schleswig-Holstein)"], 
"25889": ["Uelvesb\u00fcll", "Uelvesb\u00fcll (Schleswig-Holstein)", "Witzwort", "Witzwort (Schleswig-Holstein)"], 
"25899": ["Bosb\u00fcll", "Bosb\u00fcll (Schleswig-Holstein)", "Dageb\u00fcll", "Dageb\u00fcll (Schleswig-Holstein)", "Galmsb\u00fcll", "Galmsb\u00fcll (Schleswig-Holstein)", "Gasthafen", "Gotteskoogdeich", "Katzh\u00f6rn", "Kleinkoogsdeich", "Klixb\u00fcll", "Klixb\u00fcll (Schleswig-Holstein)", "Nieb\u00fcll", "Nieb\u00fcll (Schleswig-Holstein)", "Osterdeich"], 
"25917": ["Achtrup", "Enge-Sande", "Enge-Sande (Nordfriesland)", "Leck", "Nordfriesland-Achtrup", "Nordfriesland-Leck", "Nordfriesland-Sprakeb\u00fcll", "Nordfriesland-Stadum", "Nordfriesland-Tinningstedt", "Sprakeb\u00fcll", "Stadum", "Tinningstedt"], 
"25920": ["Nordfriesland-Stedesand", "Risum-Lindholm", "Risum-Lindholm (Nordfriesland)", "Stedesand"], 
"25923": ["Braderup", "Ellh\u00f6ft", "Hattersb\u00fcllhallig", "Holm", "Humptrup", "Lexgaard", "Nordfriesland-Braderup", "Nordfriesland-Ellh\u00f6ft", "Nordfriesland-Holm", "Nordfriesland-Humptrup", "Nordfriesland-Lexgaard", "Nordfriesland-S\u00fcderl\u00fcgum", "Nordfriesland-Uphusum", "S\u00fcderl\u00fcgum", "Uphusum"], 
"25924": ["Emmelsb\u00fcll-Horsb\u00fcll", "Emmelsb\u00fcll-Horsb\u00fcll (Nordfriesland)", "Friedrich-Wilhelm-L\u00fcbke-Koog", "Friedrich-Wilhelm-L\u00fcbke-Koog (Nordfriesland)", "Klanxb\u00fcll", "Nordfriesland-Klanxb\u00fcll", "Nordfriesland-Roden\u00e4s", "Roden\u00e4s"], 
"25926": ["Bramstedtlund", "Karlum", "Ladelund", "Nordfriesland-Bramstedtlund", "Nordfriesland-Karlum", "Nordfriesland-Ladelund", "Nordfriesland-Westre", "Westre"], 
"25927": ["Aventoft", "Neukirchen", "Nordfriesland-Aventoft", "Nordfriesland-Neukirchen"], 
"25930": ["Boldixum"], 
"25938": ["Alkersum", "Borgsum", "Dunsum", "F\u00f6hr", "Klintum", "Midlum", "Nieblum", "Nordfriesland-Alkersum", "Nordfriesland-Borgsum", "Nordfriesland-Dunsum", "Nordfriesland-Midlum", "Nordfriesland-Nieblum", "Nordfriesland-Oevenum", "Nordfriesland-Oldsum", "Nordfriesland-S\u00fcderende", "Nordfriesland-Utersum", "Nordfriesland-Witsum", "Nordfriesland-Wrixum", "Nordfriesland-Wyk", "Oevenum", "Oldsum", "S\u00fcderende", "Utersum", "Witsum", "Wrixum", "Wyk", "Wyk auf F\u00f6hr"], 
"25946": ["Amrum", "Gro\u00dfd\u00fcn", "Nebel", "Norddorf", "Norddorf auf Amrum", "Nordfriesland-Nebel", "Nordfriesland-Norddorf", "Nordfriesland-Wittd\u00fcn", "Westerheide", "Wittd\u00fcn", "Wittd\u00fcn auf Amrum"], 
"25980": ["Archsum", "Keitum", "Morsum", "Nordfriesland-Sylt", "Rantum", "Sylt", "Sylt-Ost", "Westerland"], 
"25992": ["Jugendseeheim Kassel", "List", "List auf Sylt", "List p\u00e5 Sild", "List \u00fcp S\u00f6l", "Nordfriesland-List", "Vogelkoje"], 
"25996": ["Wenningstedt-Braderup", "Wenningstedt-Braderup (Nordfriesland)", "Wenningstedt-Braderup (Sylt)"], 
"25997": ["H\u00f6rnum", "H\u00f6rnum (Sylt)", "Nordfriesland-H\u00f6rnum"], 
"25999": ["Kampen", "Kampen (Sylt)", "Nordfriesland-Kampen"]}